MANIFEST.in
README.md
requirements.txt
setup.py
ggseg/__init__.py
ggseg.egg-info/PKG-INFO
ggseg.egg-info/SOURCES.txt
ggseg.egg-info/dependency_links.txt
ggseg.egg-info/requires.txt
ggseg.egg-info/top_level.txt
ggseg/data/aseg/3rd-Ventricle
ggseg/data/aseg/4th-Ventricle
ggseg/data/aseg/Brain-Stem
ggseg/data/aseg/CC_Anterior
ggseg/data/aseg/CC_Central
ggseg/data/aseg/CC_Mid_Anterior
ggseg/data/aseg/CC_Mid_Posterior
ggseg/data/aseg/CC_Posterior
ggseg/data/aseg/Cerebellum-Cortex
ggseg/data/aseg/Cerebellum-White-Matter
ggseg/data/aseg/Coronal
ggseg/data/aseg/Left-Amygdala
ggseg/data/aseg/Left-Caudate
ggseg/data/aseg/Left-Hippocampus
ggseg/data/aseg/Left-Lateral-Ventricle
ggseg/data/aseg/Left-Pallidum
ggseg/data/aseg/Left-Putamen
ggseg/data/aseg/Left-Thalamus
ggseg/data/aseg/Left-VentralDC
ggseg/data/aseg/Right-Amygdala
ggseg/data/aseg/Right-Caudate
ggseg/data/aseg/Right-Hippocampus
ggseg/data/aseg/Right-Lateral-Ventricle
ggseg/data/aseg/Right-Pallidum
ggseg/data/aseg/Right-Putamen
ggseg/data/aseg/Right-Thalamus
ggseg/data/aseg/Right-VentralDC
ggseg/data/aseg/Sagittal
ggseg/data/dk/NA_left
ggseg/data/dk/NA_right
ggseg/data/dk/bankssts_left
ggseg/data/dk/bankssts_right
ggseg/data/dk/caudalanteriorcingulate_left
ggseg/data/dk/caudalanteriorcingulate_right
ggseg/data/dk/caudalmiddlefrontal_left
ggseg/data/dk/caudalmiddlefrontal_right
ggseg/data/dk/corpuscallosum_left
ggseg/data/dk/corpuscallosum_right
ggseg/data/dk/cuneus_left
ggseg/data/dk/cuneus_right
ggseg/data/dk/entorhinal_left
ggseg/data/dk/entorhinal_right
ggseg/data/dk/fusiform_left
ggseg/data/dk/fusiform_right
ggseg/data/dk/inferiorparietal_left
ggseg/data/dk/inferiorparietal_right
ggseg/data/dk/inferiortemporal_left
ggseg/data/dk/inferiortemporal_right
ggseg/data/dk/insula_left
ggseg/data/dk/insula_right
ggseg/data/dk/isthmuscingulate_left
ggseg/data/dk/isthmuscingulate_right
ggseg/data/dk/lateral_left
ggseg/data/dk/lateral_right
ggseg/data/dk/lateraloccipital_left
ggseg/data/dk/lateraloccipital_right
ggseg/data/dk/lateralorbitofrontal_left
ggseg/data/dk/lateralorbitofrontal_right
ggseg/data/dk/lingual_left
ggseg/data/dk/lingual_right
