Metadata-Version: 2.1
Name: ggseg
Version: 0.1a3
Summary: Python module for ggseg-like visualizations
Home-page: https://github.com/ggseg/python-ggseg
Author: Greg Operto
Author-email: goperto@barcelonabeta.org
License: MIT
Platform: any
Classifier: Intended Audience :: Developers
Classifier: Intended Audience :: Science/Research
Classifier: Intended Audience :: Education
Classifier: License :: OSI Approved :: MIT License
Classifier: Operating System :: OS Independent
Classifier: Topic :: Scientific/Engineering
Classifier: Topic :: Utilities
Classifier: Programming Language :: Python :: 3.8
